[
    {
        "fechaHora": "2024-03-25 15:49",
        "tareasCreadas": 0,
        "tareasModificadas": 0,
        "tareasFallidas": 0,
        "tareasNoModificadas": 48,
        "estado": "Con Éxito",
        "detalle": "resultados/resumen_ejecucion_20240325_155642.html"
    },
    {
        "fechaHora": "2024-03-25 15:34",
        "tareasCreadas": 0,
        "tareasModificadas": 0,
        "tareasFallidas": 0,
        "tareasNoModificadas": 48,
        "estado": "Con Éxito",
        "detalle": "resultados/resumen_ejecucion_20240325_154038.html"
    },
    {
        "fechaHora": "2024-03-25 15:22",
        "tareasCreadas": 0,
        "tareasModificadas": 0,
        "tareasFallidas": 0,
        "tareasNoModificadas": 48,
        "estado": "Con Éxito",
        "detalle": "resultados/resumen_ejecucion_20240325_152616.html"
    },
    {
        "fechaHora": "2024-03-25 15:05",
        "tareasCreadas": 0,
        "tareasModificadas": 0,
        "tareasFallidas": 0,
        "tareasNoModificadas": 48,
        "estado": "Con Éxito",
        "detalle": "resultados/resumen_ejecucion_20240325_151026.html"
    },
    {
        "fechaHora": "2024-03-25 14:49",
        "tareasCreadas": 0,
        "tareasModificadas": 0,
        "tareasFallidas": 0,
        "tareasNoModificadas": 46,
        "estado": "Con Éxito",
        "detalle": "resultados/resumen_ejecucion_20240325_145435.html"
    },
    {
        "fechaHora": "2024-03-25 14:34",
        "tareasCreadas": 0,
        "tareasModificadas": 0,
        "tareasFallidas": 0,
        "tareasNoModificadas": 43,
        "estado": "Con Éxito",
        "detalle": "resultados/resumen_ejecucion_20240325_144002.html"
    },
    {
        "fechaHora": "2024-03-25 14:22",
        "tareasCreadas": 0,
        "tareasModificadas": 0,
        "tareasFallidas": 0,
        "tareasNoModificadas": 43,
        "estado": "Con Éxito",
        "detalle": "resultados/resumen_ejecucion_20240325_142935.html"
    },
    {
        "fechaHora": "2024-03-25 14:06",
        "tareasCreadas": 0,
        "tareasModificadas": 0,
        "tareasFallidas": 0,
        "tareasNoModificadas": 42,
        "estado": "Con Éxito",
        "detalle": "resultados/resumen_ejecucion_20240325_141118.html"
    },
    {
        "fechaHora": "2024-03-25 13:52",
        "tareasCreadas": 0,
        "tareasModificadas": 0,
        "tareasFallidas": 0,
        "tareasNoModificadas": 42,
        "estado": "Con Éxito",
        "detalle": "resultados/resumen_ejecucion_20240325_135731.html"
    },
    {
        "fechaHora": "2024-03-25 13:40",
        "tareasCreadas": 0,
        "tareasModificadas": 0,
        "tareasFallidas": 0,
        "tareasNoModificadas": 39,
        "estado": "Con Éxito",
        "detalle": "resultados/resumen_ejecucion_20240325_134517.html"
    },
    {
        "fechaHora": "2024-03-25 13:25",
        "tareasCreadas": 0,
        "tareasModificadas": 1,
        "tareasFallidas": 0,
        "tareasNoModificadas": 38,
        "estado": "Con Éxito",
        "detalle": "resultados/resumen_ejecucion_20240325_132958.html"
    },
    {
        "fechaHora": "2024-03-25 13:08",
        "tareasCreadas": 0,
        "tareasModificadas": 0,
        "tareasFallidas": 0,
        "tareasNoModificadas": 38,
        "estado": "Con Éxito",
        "detalle": "resultados/resumen_ejecucion_20240325_131147.html"
    },
    {
        "fechaHora": "2024-03-25 12:49",
        "tareasCreadas": 0,
        "tareasModificadas": 0,
        "tareasFallidas": 0,
        "tareasNoModificadas": 38,
        "estado": "Con Éxito",
        "detalle": "resultados/resumen_ejecucion_20240325_125329.html"
    },
    {
        "fechaHora": "2024-03-25 12:34",
        "tareasCreadas": 0,
        "tareasModificadas": 0,
        "tareasFallidas": 0,
        "tareasNoModificadas": 38,
        "estado": "Con Éxito",
        "detalle": "resultados/resumen_ejecucion_20240325_124133.html"
    },
    {
        "fechaHora": "2024-03-25 12:20",
        "tareasCreadas": 0,
        "tareasModificadas": 0,
        "tareasFallidas": 0,
        "tareasNoModificadas": 38,
        "estado": "Con Éxito",
        "detalle": "resultados/resumen_ejecucion_20240325_122424.html"
    },
    {
        "fechaHora": "2024-03-25 12:05",
        "tareasCreadas": 0,
        "tareasModificadas": 0,
        "tareasFallidas": 0,
        "tareasNoModificadas": 38,
        "estado": "Con Éxito",
        "detalle": "resultados/resumen_ejecucion_20240325_121104.html"
    },
    {
        "fechaHora": "2024-03-25 11:49",
        "tareasCreadas": 0,
        "tareasModificadas": 0,
        "tareasFallidas": 0,
        "tareasNoModificadas": 38,
        "estado": "Con Éxito",
        "detalle": "resultados/resumen_ejecucion_20240325_115437.html"
    },
    {
        "fechaHora": "2024-03-25 11:22",
        "tareasCreadas": 0,
        "tareasModificadas": 1,
        "tareasFallidas": 0,
        "tareasNoModificadas": 36,
        "estado": "Con Éxito",
        "detalle": "resultados/resumen_ejecucion_20240325_112847.html"
    },
    {
        "fechaHora": "2024-03-25 11:06",
        "tareasCreadas": 0,
        "tareasModificadas": 0,
        "tareasFallidas": 0,
        "tareasNoModificadas": 37,
        "estado": "Con Éxito",
        "detalle": "resultados/resumen_ejecucion_20240325_111133.html"
    },
    {
        "fechaHora": "2024-03-25 10:49",
        "tareasCreadas": 0,
        "tareasModificadas": 0,
        "tareasFallidas": 0,
        "tareasNoModificadas": 36,
        "estado": "Con Éxito",
        "detalle": "resultados/resumen_ejecucion_20240325_105501.html"
    },
    {
        "fechaHora": "2024-03-25 10:34",
        "tareasCreadas": 0,
        "tareasModificadas": 0,
        "tareasFallidas": 0,
        "tareasNoModificadas": 36,
        "estado": "Con Éxito",
        "detalle": "resultados/resumen_ejecucion_20240325_104119.html"
    },
    {
        "fechaHora": "2024-03-25 10:21",
        "tareasCreadas": 0,
        "tareasModificadas": 2,
        "tareasFallidas": 0,
        "tareasNoModificadas": 30,
        "estado": "Con Éxito",
        "detalle": "resultados/resumen_ejecucion_20240325_102532.html"
    },
    {
        "fechaHora": "2024-03-25 10:06",
        "tareasCreadas": 0,
        "tareasModificadas": 15,
        "tareasFallidas": 0,
        "tareasNoModificadas": 12,
        "estado": "Con Éxito",
        "detalle": "resultados/resumen_ejecucion_20240325_101328.html"
    },
    {
        "fechaHora": "2024-03-25 09:49",
        "tareasCreadas": 0,
        "tareasModificadas": 2,
        "tareasFallidas": 0,
        "tareasNoModificadas": 12,
        "estado": "Con Éxito",
        "detalle": "resultados/resumen_ejecucion_20240325_095314.html"
    },
    {
        "fechaHora": "2024-03-25 09:34",
        "tareasCreadas": 0,
        "tareasModificadas": 1,
        "tareasFallidas": 0,
        "tareasNoModificadas": 11,
        "estado": "Con Éxito",
        "detalle": "resultados/resumen_ejecucion_20240325_093820.html"
    },
    {
        "fechaHora": "2024-03-25 09:24",
        "tareasCreadas": 0,
        "tareasModificadas": 0,
        "tareasFallidas": 0,
        "tareasNoModificadas": 11,
        "estado": "Con Éxito",
        "detalle": "resultados/resumen_ejecucion_20240325_092842.html"
    },
    {
        "fechaHora": "2024-03-25 09:08",
        "tareasCreadas": 0,
        "tareasModificadas": 2,
        "tareasFallidas": 0,
        "tareasNoModificadas": 9,
        "estado": "Con Éxito",
        "detalle": "resultados/resumen_ejecucion_20240325_091349.html"
    },
    {
        "fechaHora": "2024-03-25 08:49",
        "tareasCreadas": 0,
        "tareasModificadas": 2,
        "tareasFallidas": 0,
        "tareasNoModificadas": 4,
        "estado": "Con Éxito",
        "detalle": "resultados/resumen_ejecucion_20240325_085313.html"
    },
    {
        "fechaHora": "2024-03-25 08:34",
        "tareasCreadas": 0,
        "tareasModificadas": 1,
        "tareasFallidas": 0,
        "tareasNoModificadas": 3,
        "estado": "Con Éxito",
        "detalle": "resultados/resumen_ejecucion_20240325_083929.html"
    },
    {
        "fechaHora": "2024-03-25 08:20",
        "tareasCreadas": 0,
        "tareasModificadas": 0,
        "tareasFallidas": 0,
        "tareasNoModificadas": 3,
        "estado": "Con Éxito",
        "detalle": "resultados/resumen_ejecucion_20240325_082416.html"
    },
    {
        "fechaHora": "2024-03-25 08:06",
        "tareasCreadas": 1,
        "tareasModificadas": 1,
        "tareasFallidas": 0,
        "tareasNoModificadas": 1,
        "estado": "Con Éxito",
        "detalle": "resultados/resumen_ejecucion_20240325_081037.html"
    },
    {
        "fechaHora": "2024-03-22 15:47",
        "tareasCreadas": 0,
        "tareasModificadas": 0,
        "tareasFallidas": 0,
        "tareasNoModificadas": 34,
        "estado": "Con Éxito",
        "detalle": "resultados/resumen_ejecucion_20240322_155027.html"
    },
    {
        "fechaHora": "2024-03-22 15:32",
        "tareasCreadas": 0,
        "tareasModificadas": 0,
        "tareasFallidas": 0,
        "tareasNoModificadas": 34,
        "estado": "Con Éxito",
        "detalle": "resultados/resumen_ejecucion_20240322_153715.html"
    },
    {
        "fechaHora": "2024-03-22 15:20",
        "tareasCreadas": 0,
        "tareasModificadas": 0,
        "tareasFallidas": 0,
        "tareasNoModificadas": 34,
        "estado": "Con Éxito",
        "detalle": "resultados/resumen_ejecucion_20240322_152702.html"
    },
    {
        "fechaHora": "2024-03-22 15:02",
        "tareasCreadas": 0,
        "tareasModificadas": 0,
        "tareasFallidas": 0,
        "tareasNoModificadas": 34,
        "estado": "Con Éxito",
        "detalle": "resultados/resumen_ejecucion_20240322_150658.html"
    },
    {
        "fechaHora": "2024-03-22 14:47",
        "tareasCreadas": 0,
        "tareasModificadas": 0,
        "tareasFallidas": 0,
        "tareasNoModificadas": 34,
        "estado": "Con Éxito",
        "detalle": "resultados/resumen_ejecucion_20240322_145249.html"
    },
    {
        "fechaHora": "2024-03-22 14:32",
        "tareasCreadas": 0,
        "tareasModificadas": 1,
        "tareasFallidas": 0,
        "tareasNoModificadas": 32,
        "estado": "Con Éxito",
        "detalle": "resultados/resumen_ejecucion_20240322_143941.html"
    },
    {
        "fechaHora": "2024-03-22 14:19",
        "tareasCreadas": 2,
        "tareasModificadas": 5,
        "tareasFallidas": 0,
        "tareasNoModificadas": 25,
        "estado": "Con Éxito",
        "detalle": "resultados/resumen_ejecucion_20240322_142448.html"
    },
    {
        "fechaHora": "2024-03-22 14:02",
        "tareasCreadas": 0,
        "tareasModificadas": 3,
        "tareasFallidas": 0,
        "tareasNoModificadas": 20,
        "estado": "Con Éxito",
        "detalle": "resultados/resumen_ejecucion_20240322_140713.html"
    },
    {
        "fechaHora": "2024-03-22 13:49",
        "tareasCreadas": 0,
        "tareasModificadas": 0,
        "tareasFallidas": 0,
        "tareasNoModificadas": 22,
        "estado": "Con Éxito",
        "detalle": "resultados/resumen_ejecucion_20240322_135412.html"
    },
    {
        "fechaHora": "2024-03-22 13:37",
        "tareasCreadas": 0,
        "tareasModificadas": 5,
        "tareasFallidas": 0,
        "tareasNoModificadas": 15,
        "estado": "Con Éxito",
        "detalle": "resultados/resumen_ejecucion_20240322_134616.html"
    },
    {
        "fechaHora": "2024-03-22 13:22",
        "tareasCreadas": 0,
        "tareasModificadas": 1,
        "tareasFallidas": 0,
        "tareasNoModificadas": 15,
        "estado": "Con Éxito",
        "detalle": "resultados/resumen_ejecucion_20240322_132836.html"
    },
    {
        "fechaHora": "2024-03-22 13:03",
        "tareasCreadas": 0,
        "tareasModificadas": 0,
        "tareasFallidas": 0,
        "tareasNoModificadas": 16,
        "estado": "Con Éxito",
        "detalle": "resultados/resumen_ejecucion_20240322_131035.html"
    },
    {
        "fechaHora": "2024-03-22 12:46",
        "tareasCreadas": 0,
        "tareasModificadas": 0,
        "tareasFallidas": 0,
        "tareasNoModificadas": 16,
        "estado": "Con Éxito",
        "detalle": "resultados/resumen_ejecucion_20240322_125104.html"
    },
    {
        "fechaHora": "2024-03-22 12:32",
        "tareasCreadas": 0,
        "tareasModificadas": 0,
        "tareasFallidas": 0,
        "tareasNoModificadas": 16,
        "estado": "Con Éxito",
        "detalle": "resultados/resumen_ejecucion_20240322_123742.html"
    },
    {
        "fechaHora": "2024-03-22 12:17",
        "tareasCreadas": 0,
        "tareasModificadas": 0,
        "tareasFallidas": 0,
        "tareasNoModificadas": 16,
        "estado": "Con Éxito",
        "detalle": "resultados/resumen_ejecucion_20240322_122133.html"
    },
    {
        "fechaHora": "2024-03-22 12:02",
        "tareasCreadas": 0,
        "tareasModificadas": 0,
        "tareasFallidas": 0,
        "tareasNoModificadas": 14,
        "estado": "Con Éxito",
        "detalle": "resultados/resumen_ejecucion_20240322_120457.html"
    },
    {
        "fechaHora": "2024-03-22 11:46",
        "tareasCreadas": 0,
        "tareasModificadas": 0,
        "tareasFallidas": 0,
        "tareasNoModificadas": 14,
        "estado": "Con Éxito",
        "detalle": "resultados/resumen_ejecucion_20240322_115235.html"
    },
    {
        "fechaHora": "2024-03-22 11:32",
        "tareasCreadas": 0,
        "tareasModificadas": 0,
        "tareasFallidas": 0,
        "tareasNoModificadas": 14,
        "estado": "Con Éxito",
        "detalle": "resultados/resumen_ejecucion_20240322_113632.html"
    },
    {
        "fechaHora": "2024-03-22 11:20",
        "tareasCreadas": 0,
        "tareasModificadas": 0,
        "tareasFallidas": 0,
        "tareasNoModificadas": 14,
        "estado": "Con Éxito",
        "detalle": "resultados/resumen_ejecucion_20240322_112513.html"
    }
]